calour/__init__.py
calour/_dendrogram.py
calour/_doc.py
calour/_testing.py
calour/amplicon_experiment.py
calour/analysis.py
calour/calour.config
calour/database.py
calour/dsfdr.py
calour/experiment.py
calour/export_html.py
calour/export_html_template.html
calour/filtering.py
calour/io.py
calour/log.cfg
calour/manipulation.py
calour/ms1_experiment.py
calour/plotting.py
calour/ratio_experiment.py
calour/sorting.py
calour/training.py
calour/transforming.py
calour/util.py
calour/heatmap/__init__.py
calour/heatmap/heatmap.py
calour/heatmap/plotgui.py
calour/heatmap/plotgui_cli.py
calour/heatmap/plotgui_jupyter.py
calour/heatmap/plotgui_qt5.py
calour-2019.5.1.dist-info/COPYING.txt
calour-2019.5.1.dist-info/METADATA
calour-2019.5.1.dist-info/WHEEL
calour-2019.5.1.dist-info/top_level.txt
calour-2019.5.1.dist-info/RECORD
