Metadata-Version: 2.1
Name: calour
Version: 2019.5.1
Summary: CALOUR: exploratory and interactive microbiome analyses based on heatmap
Home-page: http://biocore.github.io/calour
Author: calour development team
Author-email: zhenjiang.xu@gmail.com
Maintainer: calour development team
License: BSD
Keywords: microbiome heatmap analysis bioinformatics
Classifier: Development Status :: 2 - Pre-Alpha
Classifier: License :: OSI Approved :: BSD License
Classifier: Environment :: Console
Classifier: Topic :: Software Development :: Libraries :: Application Frameworks
Classifier: Topic :: Scientific/Engineering
Classifier: Topic :: Scientific/Engineering :: Bio-Informatics
Classifier: Programming Language :: Python
Classifier: Programming Language :: Python :: 3
Classifier: Programming Language :: Python :: 3.6
Classifier: Programming Language :: Python :: 3.7
Classifier: Programming Language :: Python :: 3.8
Classifier: Operating System :: Unix
Classifier: Operating System :: POSIX
Classifier: Operating System :: MacOS :: MacOS X
Classifier: Operating System :: Microsoft :: Windows
License-File: COPYING.txt
Requires-Dist: numpy
Requires-Dist: scipy
Requires-Dist: pandas
Requires-Dist: matplotlib (>=2.0)
Requires-Dist: scikit-learn (>=0.19.1)
Requires-Dist: biom-format
Requires-Dist: statsmodels
Requires-Dist: docrep
Provides-Extra: coverage
Requires-Dist: coveralls ; extra == 'coverage'
Provides-Extra: dendrogram
Requires-Dist: scikit-bio (>=0.5.1) ; extra == 'dendrogram'
Provides-Extra: doc
Requires-Dist: Sphinx (>=1.4) ; extra == 'doc'
Requires-Dist: sphinx-autodoc-typehints ; extra == 'doc'
Requires-Dist: nbsphinx ; extra == 'doc'
Provides-Extra: test
Requires-Dist: nose ; extra == 'test'
Requires-Dist: pep8 ; extra == 'test'
Requires-Dist: flake8 ; extra == 'test'
Requires-Dist: scikit-bio (>=0.5.1) ; extra == 'test'
Requires-Dist: ipywidgets ; extra == 'test'
